ecomegane/__init__.py
ecomegane/ecomegane.py
ecomegane-1.0.0.dist-info/LICENSE.md
ecomegane-1.0.0.dist-info/METADATA
ecomegane-1.0.0.dist-info/WHEEL
ecomegane-1.0.0.dist-info/top_level.txt
ecomegane-1.0.0.dist-info/RECORD
