Metadata-Version: 2.1
Name: ecomegane
Version: 1.0.0
Summary: Download data from Eco-Megane PV monitoring platform.
Home-page: https://github.com/dliberat/ecomegane
Author: Dan Liberatori
Author-email: daniel.liberatori@gmail.com
License: UNKNOWN
Project-URL: Bug Tracker, https://github.com/dliberat/ecomegane/issues
Platform: UNKNOWN
Classifier: Programming Language :: Python :: 3
Classifier: License :: OSI Approved :: MIT License
Classifier: Operating System :: OS Independent
Requires-Python: >=3.6
Requires-Dist: requests
Requires-Dist: beautifulsoup4
Requires-Dist: lxml
